Metadata-Version: 2.1
Name: jsonschema-typed
Version: 0.8.1
Summary: Automatic type annotations from JSON schemas
Home-page: https://github.com/jsonschema-typed/jsonschema-typed
Author: Erick Peirson, Bendik Samseth, Felix von Drigalski
Author-email: FvDrigalski@gmail.com
License: MIT
Classifier: Development Status :: 4 - Beta
Classifier: Environment :: Console
Classifier: Intended Audience :: Developers
Classifier: License :: OSI Approved :: MIT License
Classifier: Operating System :: OS Independent
Classifier: Programming Language :: Python
Classifier: Programming Language :: Python :: 3.7
Classifier: Programming Language :: Python :: 3.8
Classifier: Programming Language :: Python :: 3 :: Only
Classifier: Topic :: Software Development :: Quality Assurance
Classifier: Topic :: Software Development :: Code Generators
Classifier: Topic :: Software Development :: Testing
Classifier: Typing :: Typed
Requires-Python: >=3.7
License-File: LICENSE
Requires-Dist: jsonschema >=3.2.0
Requires-Dist: mypy >=0.761
